google/cloud/apihub/__init__.py
google/cloud/apihub/gapic_version.py
google/cloud/apihub/py.typed
google/cloud/apihub_v1/__init__.py
google/cloud/apihub_v1/gapic_metadata.json
google/cloud/apihub_v1/gapic_version.py
google/cloud/apihub_v1/py.typed
google/cloud/apihub_v1/services/__init__.py
google/cloud/apihub_v1/services/api_hub/__init__.py
google/cloud/apihub_v1/services/api_hub/async_client.py
google/cloud/apihub_v1/services/api_hub/client.py
google/cloud/apihub_v1/services/api_hub/pagers.py
google/cloud/apihub_v1/services/api_hub/transports/__init__.py
google/cloud/apihub_v1/services/api_hub/transports/base.py
google/cloud/apihub_v1/services/api_hub/transports/grpc.py
google/cloud/apihub_v1/services/api_hub/transports/grpc_asyncio.py
google/cloud/apihub_v1/services/api_hub/transports/rest.py
google/cloud/apihub_v1/services/api_hub/transports/rest_base.py
google/cloud/apihub_v1/services/api_hub_collect/__init__.py
google/cloud/apihub_v1/services/api_hub_collect/async_client.py
google/cloud/apihub_v1/services/api_hub_collect/client.py
google/cloud/apihub_v1/services/api_hub_collect/transports/__init__.py
google/cloud/apihub_v1/services/api_hub_collect/transports/base.py
google/cloud/apihub_v1/services/api_hub_collect/transports/grpc.py
google/cloud/apihub_v1/services/api_hub_collect/transports/grpc_asyncio.py
google/cloud/apihub_v1/services/api_hub_collect/transports/rest.py
google/cloud/apihub_v1/services/api_hub_collect/transports/rest_base.py
google/cloud/apihub_v1/services/api_hub_curate/__init__.py
google/cloud/apihub_v1/services/api_hub_curate/async_client.py
google/cloud/apihub_v1/services/api_hub_curate/client.py
google/cloud/apihub_v1/services/api_hub_curate/pagers.py
google/cloud/apihub_v1/services/api_hub_curate/transports/__init__.py
google/cloud/apihub_v1/services/api_hub_curate/transports/base.py
google/cloud/apihub_v1/services/api_hub_curate/transports/grpc.py
google/cloud/apihub_v1/services/api_hub_curate/transports/grpc_asyncio.py
google_cloud_apihub-0.5.0.dist-info/licenses/LICENSE
google_cloud_apihub-0.5.0.dist-info/METADATA
google_cloud_apihub-0.5.0.dist-info/WHEEL
google_cloud_apihub-0.5.0.dist-info/top_level.txt
google_cloud_apihub-0.5.0.dist-info/RECORD
